marshmallowqa/__init__.py
marshmallowqa/action.py
marshmallowqa/const.py
marshmallowqa/cookie.py
marshmallowqa/errors.py
marshmallowqa/marshmallow.py
marshmallowqa/version.py
marshmallowqa_py-0.7.2.dist-info/METADATA
marshmallowqa_py-0.7.2.dist-info/WHEEL
marshmallowqa_py-0.7.2.dist-info/licenses/LICENSE
marshmallowqa_py-0.7.2.dist-info/RECORD
