Metadata-Version: 2.3
Name: marshmallowqa.py
Version: 0.7.2
Summary: Add your description here
Author-email: "2.30am" <111672334+am230@users.noreply.github.com>
License-File: LICENSE
Requires-Python: >=3.8
Requires-Dist: aiohttp>=3.9.5
Requires-Dist: beautifulsoup4>=4.12.3
Requires-Dist: pydantic>=2.7.4
Requires-Dist: rookiepy>=0.5.1
